enocean/__init__.py
enocean/consolelogger.py
enocean/decorators.py
enocean/utils.py
enocean/communicators/__init__.py
enocean/communicators/communicator.py
enocean/communicators/serialcommunicator.py
enocean/communicators/tcpcommunicator.py
enocean/communicators/utils.py
enocean/protocol/EEP.xml
enocean/protocol/__init__.py
enocean/protocol/constants.py
enocean/protocol/crc8.py
enocean/protocol/eep.py
enocean/protocol/packet.py
enocean_tempfixup-0.50.2.data/scripts/enocean_example.py
enocean_tempfixup-0.50.2.dist-info/LICENSE
enocean_tempfixup-0.50.2.dist-info/METADATA
enocean_tempfixup-0.50.2.dist-info/WHEEL
enocean_tempfixup-0.50.2.dist-info/top_level.txt
enocean_tempfixup-0.50.2.dist-info/RECORD
