Metadata-Version: 2.1
Name: enocean-tempfixup
Version: 0.50.2
Summary: EnOcean serial protocol implementation
Home-page: https://github.com/kipe/enocean
Author: Felix Kluge
Author-email: felix_kluge@wh2.tu-dresden.de
License: UNKNOWN
Platform: UNKNOWN
Requires-Dist: enum-compat (>=0.0.2)
Requires-Dist: pyserial (>=3.0)
Requires-Dist: beautifulsoup4 (>=4.3.2)
